[[{"episode": "24", "image_url": "https://cdnimg.xyz/cover/ninjala.png", "link": "/ninjala/24", "time": "38 minutes ago", "title": "Ninjala"}, {"episode": "11", "image_url": "https://cdnimg.xyz/cover/onipan.png", "link": "/onipan/11", "time": "58 minutes ago", "title": "Onipan!"}, {"episode": "18-19", "image_url": "https://cdnimg.xyz/cover/super-psycho-love.png", "link": "/super-psycho-love/18-19/12", "time": "1 hour ago", "title": "Super Psycho Love"}, {"episode": "62", "image_url": "https://cdnimg.xyz/cover/i-got-you-2022.png", "link": "/i-got-you-2022/62", "time": "1 hour ago", "title": "I Got You (2022)"}, {"episode": "24", "image_url": "https://cdnimg.xyz/cover/i-am-his-first-love.png", "link": "/i-am-his-first-love/24", "time": "1 hour ago", "title": "I Am His First Love"}, {"episode": "12", "image_url": "https://cdnimg.xyz/cover/i-am-legend-2nd-season.png", "link": "/i-am-legend-2nd-season/12/9", "time": "1 hour ago", "title": "I AM Legend 2nd Season"}, {"episode": "149", "image_url": "https://cdnimg.xyz/cover/king-of-the-phoenix.png", "link": "/king-of-the-phoenix/149", "time": "1 hour ago", "title": "King of the Phoenix"}, {"episode": "7", "image_url": "https://cdnimg.xyz/cover/fake-identity-2.png", "link": "/fake-identity-2/7/3", "time": "2 hours ago", "title": "Fake Identity 2"}, {"episode": "11", "image_url": "https://cdnimg.xyz/cover/shouwa-ahozoushi-akanuke-ichiban.png", "link": "/shouwa-ahozoushi-akanuke-ichiban/11", "time": "2 hours ago", "title": "Shouwa Ahozoushi Akanuke Ichiban!"}, {"episode": "13", "image_url": "https://cdnimg.xyz/cover/chiikawa.png", "link": "/chiikawa/13", "time": "2 hours ago", "title": "Chiikawa"}, {"episode": "116", "image_url": "https://cdnimg.xyz/cover/dr-slump-arale-chan.png", "link": "/dr-slump-arale-chan/116", "time": "2 hours ago", "title": "Dr. Slump: Arale-chan"}, {"episode": "11", "image_url": "https://cdnimg.xyz/cover/shen-yin-wangzuo.png", "link": "/shen-yin-wangzuo/11", "time": "2 hours ago", "title": "Shen Yin Wangzuo"}, {"episode": "106", "image_url": "https://cdnimg.xyz/cover/wan-jie-xian-zong-5th-season.png", "link": "/wan-jie-xian-zong-5th-season/106", "time": "2 hours ago", "title": "Wan Jie Xian Zong 5th Season"}, {"episode": "219", "image_url": "https://cdnimg.xyz/cover/dubu-xiaoyao.png", "link": "/dubu-xiaoyao/219", "time": "2 hours ago", "title": "Dubu Xiaoyao"}, {"episode": "15", "image_url": "https://cdnimg.xyz/cover/qi-jie-diyi-xian.png", "link": "/qi-jie-diyi-xian/15", "time": "2 hours ago", "title": "Qi Jie Diyi Xian"}, {"episode": "19", "image_url": "https://cdnimg.xyz/cover/atasha-kawajiri-kodama-da-yo-dangerous-lifehacker-no-tadareta-seikatsu.png", "link": "/atasha-kawajiri-kodama-da-yo-dangerous-lifehacker-no-tadareta-seikatsu/19", "time": "9 hours ago", "title": "Atasha Kawajiri Kodama Da yo: Dangerous Lifehacker no Tadareta Seikatsu"}, {"episode": "11", "image_url": "https://cdnimg.xyz/cover/mahoutsukai-reimeiki.png", "link": "/mahoutsukai-reimeiki/11", "time": "9 hours ago", "title": "Mahoutsukai Reimeiki"}, {"episode": "11", "image_url": "https://cdnimg.xyz/cover/machikado-mazoku-2-choume.png", "link": "/machikado-mazoku-2-choume/11", "time": "10 hours ago", "title": "Machikado Mazoku: 2-choume"}, {"episode": "12", "image_url": "https://cdnimg.xyz/cover/gaikotsu-kishi-sama-tadaima-isekai-e-odekakechuu.png", "link": "/gaikotsu-kishi-sama-tadaima-isekai-e-odekakechuu/12", "time": "13 hours ago", "title": "Gaikotsu Kishi-sama, Tadaima Isekai e Odekakechuu"}, {"episode": "12", "image_url": "https://cdnimg.xyz/cover/komi-san-wa-comyushou-desu-2nd-season.png", "link": "/komi-san-wa-comyushou-desu-2nd-season/12", "time": "14 hours ago", "title": "Komi-san wa, Comyushou desu. 2nd Season"}, {"episode": "12", "image_url": "https://cdnimg.xyz/cover/heroine-tarumono-kiraware-heroine-to-naisho-no-oshigoto.png", "link": "/heroine-tarumono-kiraware-heroine-to-naisho-no-oshigoto/12", "time": "14 hours ago", "title": "Heroine Tarumono! Kiraware Heroine to Naisho no Oshigoto"}, {"episode": "3", "image_url": "https://cdnimg.xyz/cover/pokemon-legends-arceus-yuki-hodo-kishi-futaai.png", "link": "/pokemon-legends-arceus-yuki-hodo-kishi-futaai/3", "time": "14 hours ago", "title": "Pokemon Legends Arceus: Yuki Hodo Kishi Futaai"}, {"episode": "12", "image_url": "https://cdnimg.xyz/cover/shachiku-san-wa-youjo-yuurei-ni-iyasaretai.png", "link": "/shachiku-san-wa-youjo-yuurei-ni-iyasaretai/12", "time": "14 hours ago", "title": "Shachiku-san wa Youjo Yuurei ni Iyasaretai."}, {"episode": "6", "image_url": "https://cdnimg.xyz/cover/shishang-zui-qiang-nan-zhujiao.png", "link": "/shishang-zui-qiang-nan-zhujiao/6", "time": "23 hours ago", "title": "Shishang Zui Qiang Nan Zhujiao"}, {"episode": "243", "image_url": "https://cdnimg.xyz/cover/wan-jie-shen-zhu.png", "link": "/wan-jie-shen-zhu/243", "time": "1 day ago", "title": "Wan Jie Shen Zhu"}, {"episode": "12", "image_url": "https://cdnimg.xyz/cover/deaimon.png", "link": "/deaimon/12", "time": "1 day ago", "title": "Deaimon"}, {"episode": "12", "image_url": "https://cdnimg.xyz/cover/rpg-fudousan.png", "link": "/rpg-fudousan/12", "time": "1 day ago", "title": "RPG Fudousan"}, {"episode": "12", "image_url": "https://cdnimg.xyz/cover/tate-no-yuusha-no-nariagari-2nd-season.png", "link": "/tate-no-yuusha-no-nariagari-season-2/12", "time": "1 day ago", "title": "Tate no Yuusha no Nariagari Season 2"}, {"episode": "12", "image_url": "https://cdnimg.xyz/cover/shijou-saikyou-no-daimaou-murabito-a-ni-tensei-suru.png", "link": "/shijou-saikyou-no-daimaou-murabito-a-ni-tensei-suru/12", "time": "1 day ago", "title": "Shijou Saikyou no Daimaou, Murabito A ni Tensei suru"}, {"episode": "11", "image_url": "https://cdnimg.xyz/cover/xingji-yi-you.png", "link": "/xingji-yi-you/11", "time": "1 day ago", "title": "Xingji Yi You"}], [{"episode": "10", "image_url": "https://cdnimg.xyz/cover/heroine-tarumono-kiraware-heroine-to-naisho-no-oshigoto-dub.png", "link": "/heroine-tarumono-kiraware-heroine-to-naisho-no-oshigoto-dub/10", "time": "2 hours ago", "title": "Heroine Tarumono! Kiraware Heroine to Naisho no Oshigoto (Dub)"}, {"episode": "8", "image_url": "https://cdnimg.xyz/cover/shinka-no-mi-shiranai-uchi-ni-kachigumi-jinsei-dub.png", "link": "/shinka-no-mi-shiranai-uchi-ni-kachigumi-jinsei-dub/8", "time": "2 hours ago", "title": "Shinka no Mi: Shiranai Uchi ni Kachigumi Jinsei (Dub)"}, {"episode": "9", "image_url": "https://cdnimg.xyz/cover/tsuki-ga-michibiku-isekai-douchuu-dub.png", "link": "/tsuki-ga-michibiku-isekai-douchuu-dub/9", "time": "2 hours ago", "title": "Tsuki ga Michibiku Isekai Douchuu (Dub)"}, {"episode": "9", "image_url": "https://cdnimg.xyz/cover/gaikotsu-kishi-sama-tadaima-isekai-e-odekakechuu-dub.png", "link": "/gaikotsu-kishi-sama-tadaima-isekai-e-odekakechuu-dub/9", "time": "2 hours ago", "title": "Gaikotsu Kishi-sama, Tadaima Isekai e Odekakechuu (Dub)"}, {"episode": "9", "image_url": "https://cdnimg.xyz/cover/mahoutsukai-reimeiki-dub.png", "link": "/mahoutsukai-reimeiki-dub/9", "time": "7 hours ago", "title": "Mahoutsukai Reimeiki (Dub)"}, {"episode": "12", "image_url": "https://cdnimg.xyz/cover/ginga-eiyuu-densetsu-die-neue-these-gekitotsu-dub.png", "link": "/ginga-eiyuu-densetsu-die-neue-these-gekitotsu-dub/12", "time": "7 hours ago", "title": "Ginga Eiyuu Densetsu: Die Neue These - Gekitotsu (Dub)"}, {"episode": "5", "image_url": "https://cdnimg.xyz/cover/machikado-mazoku-2-choume-dub.png", "link": "/machikado-mazoku-2-choume-dub/5", "time": "10 hours ago", "title": "Machikado Mazoku: 2-choume (Dub)"}, {"episode": "3", "image_url": "https://cdnimg.xyz/cover/pokemon-legends-arceus-yuki-hodo-kishi-futaai-dub.png", "link": "/pokemon-legends-arceus-yuki-hodo-kishi-futaai-dub/3", "time": "14 hours ago", "title": "Pokemon Legends Arceus: Yuki Hodo Kishi Futaai (Dub)"}, {"episode": "10", "image_url": "https://cdnimg.xyz/cover/shijou-saikyou-no-daimaou-murabito-a-ni-tensei-suru-dub.png", "link": "/shijou-saikyou-no-daimaou-murabito-a-ni-tensei-suru-dub/10", "time": "1 day ago", "title": "Shijou Saikyou no Daimaou, Murabito A ni Tensei suru (Dub)"}, {"episode": "10", "image_url": "https://cdnimg.xyz/cover/estab-life-great-escape-dub.png", "link": "/estab-life-great-escape-dub/10", "time": "1 day ago", "title": "Estab-Life: Great Escape (Dub)"}, {"episode": "8", "image_url": "https://cdnimg.xyz/cover/tate-no-yuusha-no-nariagari-season-2-dub.png", "link": "/tate-no-yuusha-no-nariagari-season-2-dub/8", "time": "1 day ago", "title": "Tate no Yuusha no Nariagari Season 2 (Dub)"}, {"episode": "94", "image_url": "https://cdnimg.xyz/cover/pokemon-2019-dub.png", "link": "/pokemon-2019-dub/94", "time": "1 day ago", "title": "Pokemon (2019) (Dub)"}, {"episode": "2", "image_url": "https://cdnimg.xyz/cover/ikkitousen-extravaganza-epoch-dub.png", "link": "/ikkitousen-extravaganza-epoch-dub/2", "time": "2 days ago", "title": "Ikkitousen: Extravaganza Epoch (Dub)"}, {"episode": "10", "image_url": "https://cdnimg.xyz/cover/tomodachi-game-dub.png", "link": "/tomodachi-game-dub/10", "time": "2 days ago", "title": "Tomodachi Game (Dub)"}, {"episode": "6", "image_url": "https://cdnimg.xyz/cover/honzuki-no-gekokujou-shisho-ni-naru-tame-ni-wa-shudan-wo-erandeiraremasen-3rd-season-dub.png", "link": "/honzuki-no-gekokujou-shisho-ni-naru-tame-ni-wa-shudan-wo-erandeiraremasen-3rd-season-dub/6", "time": "2022-06-20 18:57:43", "title": "Honzuki no Gekokujou: Shisho ni Naru Tame ni wa Shudan wo Erandeiraremasen 3rd Season (Dub)"}, {"episode": "1", "image_url": "https://cdnimg.xyz/cover/kobayashi-san-chi-no-maid-dragon-s-nippon-no-omotenashi-attend-wa-dragon-desu-dub.png", "link": "/kobayashi-san-chi-no-maid-dragon-s-nippon-no-omotenashi-attend-wa-dragon-desu-dub/1", "time": "2022-06-20 18:51:51", "title": "Kobayashi-san Chi no Maid Dragon S: Nippon no Omotenashi - Attend wa Dragon Desu (Dub)"}, {"episode": "9", "image_url": "https://cdnimg.xyz/cover/lupin-iii-part-6-dub.png", "link": "/lupin-iii-part-6-dub/9", "time": "2022-06-20 00:16:56", "title": "Lupin III: Part 6 (Dub)"}, {"episode": "2", "image_url": "https://cdnimg.xyz/cover/shingeki-no-kyojin-lost-girls-dub.png", "link": "/shingeki-no-kyojin-lost-girls-dub/2", "time": "2022-06-19 19:51:15", "title": "Shingeki no Kyojin: Lost Girls (Dub)"}, {"episode": "10", "image_url": "https://cdnimg.xyz/cover/otome-game-sekai-wa-mob-ni-kibishii-sekai-desu-dub.png", "link": "/otome-game-sekai-wa-mob-ni-kibishii-sekai-desu-dub/10", "time": "2022-06-19 18:25:19", "title": "Otome Game Sekai wa Mob ni Kibishii Sekai desu (Dub)"}, {"episode": "1", "image_url": "https://cdnimg.xyz/cover/irozuku-sekai-no-ashita-kara-dub.png", "link": "/irozuku-sekai-no-ashita-kara-dub/1", "time": "2022-06-19 10:19:06", "title": "Irozuku Sekai no Ashita kara (Dub)"}, {"episode": "20", "image_url": "https://cdnimg.xyz/cover/baraou-no-souretsu-dub.png", "link": "/baraou-no-souretsu-dub/20", "time": "2022-06-19 07:19:03", "title": "Baraou no Souretsu (Dub)"}, {"episode": "26", "image_url": "https://cdnimg.xyz/cover/heat-guy-j-dub.png", "link": "/heat-guy-j-dub/26", "time": "2022-06-18 23:00:58", "title": "Heat Guy J (Dub)"}, {"episode": "9", "image_url": "https://cdnimg.xyz/cover/takt-op-destiny-dub.png", "link": "/takt-op-destiny-dub/9", "time": "2022-06-18 17:39:26", "title": "Takt Op. Destiny (Dub)"}, {"episode": "10", "image_url": "https://cdnimg.xyz/cover/love-live-nijigasaki-gakuen-school-idol-doukoukai-2nd-season-dub.png", "link": "/love-live-nijigasaki-gakuen-school-idol-doukoukai-2nd-season-dub/10", "time": "2022-06-18 17:39:00", "title": "Love Live! Nijigasaki Gakuen School Idol Doukoukai 2nd Season (Dub)"}, {"episode": "9", "image_url": "https://cdnimg.xyz/cover/ao-ashi-dub.png", "link": "/ao-ashi-dub/9", "time": "2022-06-18 17:38:36", "title": "Ao Ashi (Dub)"}, {"episode": "7", "image_url": "https://cdnimg.xyz/cover/kakkou-no-iinazuke-dub.png", "link": "/kakkou-no-iinazuke-dub/7", "time": "2022-06-18 17:38:01", "title": "Kakkou no Iinazuke (Dub)"}, {"episode": "8", "image_url": "https://cdnimg.xyz/cover/kawaii-dake-ja-nai-shikimori-san-dub.png", "link": "/kawaii-dake-ja-nai-shikimori-san-dub/8", "time": "2022-06-18 17:37:17", "title": "Kawaii dake ja Nai Shikimori-san (Dub)"}, {"episode": "6", "image_url": "https://cdnimg.xyz/cover/spriggan-ona-dub.png", "link": "/spriggan-ona-dub/6", "time": "2022-06-18 04:06:33", "title": "Spriggan (ONA) (Dub)"}, {"episode": "9", "image_url": "https://cdnimg.xyz/cover/koi-wa-sekai-seifuku-no-ato-de-dub.png", "link": "/koi-wa-sekai-seifuku-no-ato-de-dub/9", "time": "2022-06-17 19:16:34", "title": "Koi wa Sekai Seifuku no Ato de (Dub)"}, {"episode": "9", "image_url": "https://cdnimg.xyz/cover/date-a-live-iv-dub.png", "link": "/date-a-live-iv-dub/9", "time": "2022-06-17 18:47:44", "title": "Date A Live IV (Dub)"}]]