[[{"episode": "26", "image_url": "https://gogocdn.net/cover/ninjala.png", "link": "/ninjala/26", "title": "Ninjala"}, {"episode": "1", "image_url": "https://gogocdn.net/cover/bucchigire.png", "link": "/bucchigire/1", "title": "Bucchigire!"}, {"episode": "1", "image_url": "https://gogocdn.net/cover/reflect.png", "link": "/reflect/1", "title": "Reflect"}, {"episode": "20", "image_url": "https://gogocdn.net/cover/atasha-kawajiri-kodama-da-yo-dangerous-lifehacker-no-tadareta-seikatsu.png", "link": "/atasha-kawajiri-kodama-da-yo-dangerous-lifehacker-no-tadareta-seikatsu/20", "title": "Atasha Kawajiri Kodama Da yo: Dangerous Lifehacker no Tadareta Seikatsu"}, {"episode": "1", "image_url": "https://gogocdn.net/cover/yofukashi-no-uta.png", "link": "/yofukashi-no-uta/1", "title": "Yofukashi no Uta"}, {"episode": "1", "image_url": "https://gogocdn.net/cover/chimimo.png", "link": "/chimimo/1", "title": "Chimimo"}, {"episode": "40", "image_url": "https://gogocdn.net/cover/bakusou-kyoudai-lets-go-wgp.png", "link": "/bakusou-kyoudai-lets-go-wgp/40", "title": "Bakusou Kyoudai Let's & Go WGP"}, {"episode": "1", "image_url": "https://gogocdn.net/cover/kumichou-musume-to-sewagakari.png", "link": "/kumichou-musume-to-sewagakari/1", "title": "Kumichou Musume to Sewagakari"}, {"episode": "1", "image_url": "https://gogocdn.net/cover/overlord-ple-ple-pleiades-4.png", "link": "/overlord-ple-ple-pleiades-4/1", "title": "Overlord: Ple Ple Pleiades 4"}, {"episode": "25", "image_url": "https://gogocdn.net/cover/ai-no-gakkou-cuore-monogatari.png", "link": "/ai-no-gakkou-cuore-monogatari/25", "title": "Ai no Gakkou Cuore Monogatari"}, {"episode": "1", "image_url": "https://gogocdn.net/cover/shin-tennis-no-ouji-sama-u-17-world-cup.png", "link": "/shin-tennis-no-ouji-sama-u-17-world-cup/1", "title": "Shin Tennis no Ouji-sama: U-17 World Cup"}, {"episode": "7", "image_url": "https://gogocdn.net/cover/motto-majime-ni-fumajime-kaiketsu-zorori-3rd-season.png", "link": "/motto-majime-ni-fumajime-kaiketsu-zorori-3rd-season/7", "title": "Motto! Majime ni Fumajime Kaiketsu Zorori 3rd Season"}, {"episode": "1", "image_url": "https://gogocdn.net/cover/isekai-meikyuu-de-harem-wo-uncensored.png", "link": "/isekai-meikyuu-de-harem-wo-uncensored/1", "title": "Isekai Meikyuu de Harem wo (Uncensored)"}, {"episode": "1", "image_url": "https://gogocdn.net/cover/mamahaha-no-tsurego-ga-motokano-datta.png", "link": "/mamahaha-no-tsurego-ga-motokano-datta/1", "title": "Mamahaha no Tsurego ga Motokano datta"}, {"episode": "1", "image_url": "https://gogocdn.net/cover/isekai-meikyuu-de-harem-wo.png", "link": "/isekai-meikyuu-de-harem-wo/1", "title": "Isekai Meikyuu de Harem wo"}, {"episode": "1", "image_url": "https://gogocdn.net/cover/isekai-ojisan.png", "link": "/isekai-ojisan/1", "title": "Isekai Ojisan"}, {"episode": "1", "image_url": "https://gogocdn.net/cover/made-in-abyss-retsujitsu-no-ougonkyou.png", "link": "/made-in-abyss-retsujitsu-no-ougonkyou/1", "title": "Made in Abyss: Retsujitsu no Ougonkyou"}, {"episode": "1", "image_url": "https://gogocdn.net/cover/warau-arsnotoria-sun.png", "link": "/warau-arsnotoria-sun/1", "title": "Warau Arsnotoria Sun!"}, {"episode": "1", "image_url": "https://gogocdn.net/cover/jashin-chan-dropkick-x.png", "link": "/jashin-chan-dropkick-x/1", "title": "Jashin-chan Dropkick X"}, {"episode": "1", "image_url": "https://gogocdn.net/cover/tokyo-mew-mew-new.png", "link": "/tokyo-mew-mew-new/1", "title": "Tokyo Mew Mew New \u2661"}], [{"episode": "11", "image_url": "https://gogocdn.net/cover/gaikotsu-kishi-sama-tadaima-isekai-e-odekakechuu-dub.png", "link": "/gaikotsu-kishi-sama-tadaima-isekai-e-odekakechuu-dub/11", "title": "Gaikotsu Kishi-sama, Tadaima Isekai e Odekakechuu (Dub)"}, {"episode": "10", "image_url": "https://gogocdn.net/cover/shinka-no-mi-shiranai-uchi-ni-kachigumi-jinsei-dub.png", "link": "/shinka-no-mi-shiranai-uchi-ni-kachigumi-jinsei-dub/10", "title": "Shinka no Mi: Shiranai Uchi ni Kachigumi Jinsei (Dub)"}, {"episode": "11", "image_url": "https://gogocdn.net/cover/tsuki-ga-michibiku-isekai-douchuu-dub.png", "link": "/tsuki-ga-michibiku-isekai-douchuu-dub/11", "title": "Tsuki ga Michibiku Isekai Douchuu (Dub)"}, {"episode": "12", "image_url": "https://gogocdn.net/cover/heroine-tarumono-kiraware-heroine-to-naisho-no-oshigoto-dub.png", "link": "/heroine-tarumono-kiraware-heroine-to-naisho-no-oshigoto-dub/12", "title": "Heroine Tarumono! Kiraware Heroine to Naisho no Oshigoto (Dub)"}, {"episode": "11", "image_url": "https://gogocdn.net/cover/mahoutsukai-reimeiki-dub.png", "link": "/mahoutsukai-reimeiki-dub/11", "title": "Mahoutsukai Reimeiki (Dub)"}, {"episode": "22", "image_url": "https://gogocdn.net/cover/yugioh-sevens-dub.png", "link": "/yugioh-sevens-dub/22", "title": "Yu\u2606Gi\u2606Oh!: Sevens (Dub)"}, {"episode": "7", "image_url": "https://gogocdn.net/cover/machikado-mazoku-2-choume-dub.png", "link": "/machikado-mazoku-2-choume-dub/7", "title": "Machikado Mazoku: 2-choume (Dub)"}, {"episode": "818", "image_url": "https://gogocdn.net/cover/one-piece-dub.png", "link": "/one-piece-dub/818", "title": "One Piece (Dub)"}, {"episode": "10", "image_url": "https://gogocdn.net/cover/tate-no-yuusha-no-nariagari-season-2-dub.png", "link": "/tate-no-yuusha-no-nariagari-season-2-dub/10", "title": "Tate no Yuusha no Nariagari Season 2 (Dub)"}, {"episode": "12", "image_url": "https://gogocdn.net/cover/shijou-saikyou-no-daimaou-murabito-a-ni-tensei-suru-dub.png", "link": "/shijou-saikyou-no-daimaou-murabito-a-ni-tensei-suru-dub/12", "title": "Shijou Saikyou no Daimaou, Murabito A ni Tensei suru (Dub)"}, {"episode": "12", "image_url": "https://gogocdn.net/cover/estab-life-great-escape-dub.png", "link": "/estab-life-great-escape-dub/12", "title": "Estab-Life: Great Escape (Dub)"}, {"episode": "2", "image_url": "https://gogocdn.net/cover/ikkitousen-western-wolves-dub.png", "link": "/ikkitousen-western-wolves-dub/2", "title": "Ikkitousen: Western Wolves (Dub)"}, {"episode": "2", "image_url": "https://gogocdn.net/cover/shin-ikkitousen-dub.png", "link": "/shin-ikkitousen-dub/2", "title": "Shin Ikkitousen (Dub)"}, {"episode": "12", "image_url": "https://gogocdn.net/cover/tomodachi-game-dub.png", "link": "/tomodachi-game-dub/12", "title": "Tomodachi Game (Dub)"}, {"episode": "4", "image_url": "https://gogocdn.net/cover/kyoukai-senki-part-2-dub.png", "link": "/kyoukai-senki-part-2-dub/4", "title": "Kyoukai Senki Part 2 (Dub)"}, {"episode": "8", "image_url": "https://gogocdn.net/cover/honzuki-no-gekokujou-shisho-ni-naru-tame-ni-wa-shudan-wo-erandeiraremasen-3rd-season-dub.png", "link": "/honzuki-no-gekokujou-shisho-ni-naru-tame-ni-wa-shudan-wo-erandeiraremasen-3rd-season-dub/8", "title": "Honzuki no Gekokujou: Shisho ni Naru Tame ni wa Shudan wo Erandeiraremasen 3rd Season (Dub)"}, {"episode": "2", "image_url": "https://gogocdn.net/cover/fategrand-carnival-dub.png", "link": "/fategrand-carnival-dub/2", "title": "Fate/Grand Carnival (Dub)"}, {"episode": "11", "image_url": "https://gogocdn.net/cover/lupin-iii-part-6-dub.png", "link": "/lupin-iii-part-6-dub/11", "title": "Lupin III: Part 6 (Dub)"}, {"episode": "12", "image_url": "https://gogocdn.net/cover/otome-game-sekai-wa-mob-ni-kibishii-sekai-desu-dub.png", "link": "/otome-game-sekai-wa-mob-ni-kibishii-sekai-desu-dub/12", "title": "Otome Game Sekai wa Mob ni Kibishii Sekai desu (Dub)"}, {"episode": "12", "image_url": "https://gogocdn.net/cover/love-live-nijigasaki-gakuen-school-idol-doukoukai-2nd-season-dub.png", "link": "/love-live-nijigasaki-gakuen-school-idol-doukoukai-2nd-season-dub/12", "title": "Love Live! Nijigasaki Gakuen School Idol Doukoukai 2nd Season (Dub)"}]]